pyfalldown/__init__.py
pyfalldown/__main__.py
pyfalldown/main.py
pyfalldown/command/__init__.py
pyfalldown/command/add_collectible_command.py
pyfalldown/command/add_command.py
pyfalldown/command/check_over_command.py
pyfalldown/command/collect_collectibles_command.py
pyfalldown/command/command.py
pyfalldown/command/move_ball_command.py
pyfalldown/command/scroll_command.py
pyfalldown/geometry/__init__.py
pyfalldown/geometry/geometry.py
pyfalldown/state/__init__.py
pyfalldown/state/ball.py
pyfalldown/state/collectible.py
pyfalldown/state/game_item.py
pyfalldown/state/platform.py
pyfalldown/state/state.py
pyfalldown/state/velocity.py
pyfalldown/ui/__init__.py
pyfalldown/ui/config.py
pyfalldown/ui/theme.py
pyfalldown/ui/ui.py
pyfalldown-0.1.1.dist-info/METADATA
pyfalldown-0.1.1.dist-info/WHEEL
pyfalldown-0.1.1.dist-info/entry_points.txt
pyfalldown-0.1.1.dist-info/licenses/LICENSE
pyfalldown-0.1.1.dist-info/RECORD
