Metadata-Version: 2.4
Name: pyfalldown
Version: 0.1.1
Summary: Python Falldown game
Project-URL: Homepage, https://linhns.github.io/pyfalldown/
Project-URL: Repository, https://github.com/linhns/pyfalldown
Project-URL: Documentation, https://linhns.github.io/pyfalldown/
Author-email: Nguyen Son Linh <linhns59@gmail.com>
License-File: LICENSE
Keywords: python
Classifier: Intended Audience :: Developers
Classifier: Programming Language :: Python
Classifier: Programming Language :: Python :: 3
Classifier: Programming Language :: Python :: 3.10
Classifier: Programming Language :: Python :: 3.11
Classifier: Programming Language :: Python :: 3.12
Classifier: Programming Language :: Python :: 3.13
Classifier: Topic :: Software Development :: Libraries :: Python Modules
Requires-Python: <4.0,>=3.10
Requires-Dist: pygame>=2.6.1
